memhook/__init__.py
memhook/exceptions.py
memhook/memory.py
memhook/process.py
memhook/utils.py
memhook-0.1.0.dist-info/METADATA
memhook-0.1.0.dist-info/WHEEL
memhook-0.1.0.dist-info/top_level.txt
memhook-0.1.0.dist-info/RECORD
