Metadata-Version: 2.4
Name: memhook
Version: 0.1.0
Summary: Modern Python memory reading/writing library
Author: YourName
Requires-Python: >=3.8
Requires-Dist: psutil
Dynamic: author
Dynamic: description
Dynamic: description-content-type
Dynamic: requires-dist
Dynamic: requires-python
Dynamic: summary
